code2uml/__init__.py
code2uml/code2uml.py
code2uml/requirements.txt
code2uml/graph/__init__.py
code2uml/graph/diagram_converter.py
code2uml/graph/example_diagram.puml
code2uml/graph/test_converter.py
code2uml/parser/__init__.py
code2uml/parser/cpp_parser.py
code2uml/parser/java_parser.py
code2uml/parser/antlr/__init__.py
code2uml/parser/antlr/cpp/CPP14Lexer.g4
code2uml/parser/antlr/cpp/CPP14Lexer.interp
code2uml/parser/antlr/cpp/CPP14Lexer.py
code2uml/parser/antlr/cpp/CPP14Lexer.tokens
code2uml/parser/antlr/cpp/CPP14Parser.g4
code2uml/parser/antlr/cpp/CPP14Parser.interp
code2uml/parser/antlr/cpp/CPP14Parser.py
code2uml/parser/antlr/cpp/CPP14Parser.tokens
code2uml/parser/antlr/cpp/CPP14ParserBase.py
code2uml/parser/antlr/cpp/CPP14ParserListener.py
code2uml/parser/antlr/cpp/__init__.py
code2uml/parser/antlr/cpp/transformGrammar.py
code2uml/parser/antlr/java/JavaLexer.g4
code2uml/parser/antlr/java/JavaLexer.interp
code2uml/parser/antlr/java/JavaLexer.py
code2uml/parser/antlr/java/JavaLexer.tokens
code2uml/parser/antlr/java/JavaParser.g4
code2uml/parser/antlr/java/JavaParser.interp
code2uml/parser/antlr/java/JavaParser.py
code2uml/parser/antlr/java/JavaParser.tokens
code2uml/parser/antlr/java/JavaParserListener.py
code2uml/parser/antlr/java/__init__.py
code2uml/tests/code2uml_cpp.mmd
code2uml/tests/code2uml_cpp.puml
code2uml/tests/code2uml_java.mmd
code2uml/tests/code2uml_java.puml
code2uml/tests/cpp/a.cpp
code2uml/tests/cpp/a.h
code2uml/tests/cpp/test_cpp_parser.py
code2uml/tests/java/Test.java
code2uml/tests/java/com/code2uml/test/TestJavaParser.java
code2uml-0.2.5.1.dist-info/LICENSE
code2uml-0.2.5.1.dist-info/METADATA
code2uml-0.2.5.1.dist-info/WHEEL
code2uml-0.2.5.1.dist-info/entry_points.txt
code2uml-0.2.5.1.dist-info/top_level.txt
code2uml-0.2.5.1.dist-info/RECORD
