Metadata-Version: 2.1
Name: code2uml
Version: 0.2.5.1
Summary: Generate UML diagrams from source code
Home-page: https://github.com/passion-coder-min/code2uml.git
Author: min
Author-email: testmin@outlook.com
Project-URL: Bug Tracker, https://github.com/passion-coder-min/code2uml/issues
Project-URL: Documentation, https://github.com/passion-coder-min/code2uml/README.md
Project-URL: Source Code, https://github.com/passion-coder-min/code2uml.git
Classifier: Development Status :: 3 - Alpha
Classifier: Intended Audience :: Developers
Classifier: License :: OSI Approved :: MIT License
Classifier: Programming Language :: Python :: 3
Classifier: Programming Language :: Python :: 3.6
Classifier: Programming Language :: Python :: 3.7
Classifier: Programming Language :: Python :: 3.8
Classifier: Programming Language :: Python :: 3.9
Classifier: Operating System :: OS Independent
Classifier: Topic :: Software Development :: Code Generators
License-File: LICENSE
Requires-Dist: antlr4-python3-runtime
